tastysoup/__init__.py
tastysoup/core.py
tastysoup-0.2.1.dist-info/licenses/LICENSE
tastysoup-0.2.1.dist-info/METADATA
tastysoup-0.2.1.dist-info/WHEEL
tastysoup-0.2.1.dist-info/top_level.txt
tastysoup-0.2.1.dist-info/RECORD
