Metadata-Version: 2.4
Name: tastysoup
Version: 0.2.1
Summary: A tasty SEO-focused wrapper around BeautifulSoup
Home-page: https://github.com/amal-alexander
Author: Amal Alexander
Author-email: amalalex95@gmail.com
License: MIT
Classifier: Programming Language :: Python :: 3
Classifier: License :: OSI Approved :: MIT License
Classifier: Topic :: Internet :: WWW/HTTP :: Indexing/Search
Requires-Python: >=3.7
License-File: LICENSE
Requires-Dist: beautifulsoup4
Requires-Dist: requests
Requires-Dist: lxml
Dynamic: license-file
